equilibrator_cheminfo/__init__.py
equilibrator_cheminfo/_version.py
equilibrator_cheminfo/helpers.py
equilibrator_cheminfo/domain/__init__.py
equilibrator_cheminfo/domain/model/__init__.py
equilibrator_cheminfo/domain/model/abstract_chemical_species_factory.py
equilibrator_cheminfo/domain/model/abstract_chemical_species_repository.py
equilibrator_cheminfo/domain/model/abstract_domain_registry.py
equilibrator_cheminfo/domain/model/abstract_molecule.py
equilibrator_cheminfo/domain/model/chemical_species.py
equilibrator_cheminfo/domain/model/equilibrator_cheminformatics_error.py
equilibrator_cheminfo/domain/model/error_message.py
equilibrator_cheminfo/domain/model/major_microspecies.py
equilibrator_cheminfo/domain/model/manual_structure_exception_specification.py
equilibrator_cheminfo/domain/model/structure.py
equilibrator_cheminfo/domain/model/structure_identifier.py
equilibrator_cheminfo/domain/model/structures_table.py
equilibrator_cheminfo/domain/model/data/__init__.py
equilibrator_cheminfo/domain/model/data/manual_exceptions.tsv
equilibrator_cheminfo/domain/service/__init__.py
equilibrator_cheminfo/domain/service/abstract_major_microspecies_service.py
equilibrator_cheminfo/domain/service/abstract_proton_dissociation_constants_service.py
equilibrator_cheminfo/infrastructure/__init__.py
equilibrator_cheminfo/infrastructure/chemical_species_configuration.py
equilibrator_cheminfo/infrastructure/cheminformatics_backend.py
equilibrator_cheminfo/infrastructure/domain_registry.py
equilibrator_cheminfo/infrastructure/singleton.py
equilibrator_cheminfo/infrastructure/chemaxon/__init__.py
equilibrator_cheminfo/infrastructure/chemaxon/abstract_chemaxon_adapter.py
equilibrator_cheminfo/infrastructure/chemaxon/chemaxon_chemical_species_configuration.py
equilibrator_cheminfo/infrastructure/chemaxon/chemaxon_chemical_species_factory.py
equilibrator_cheminfo/infrastructure/chemaxon/chemaxon_error.py
equilibrator_cheminfo-0.15.0.dist-info/LICENSE
equilibrator_cheminfo-0.15.0.dist-info/METADATA
equilibrator_cheminfo-0.15.0.dist-info/WHEEL
equilibrator_cheminfo-0.15.0.dist-info/top_level.txt
equilibrator_cheminfo-0.15.0.dist-info/zip-safe
equilibrator_cheminfo-0.15.0.dist-info/RECORD
