Metadata-Version: 2.1
Name: equilibrator-cheminfo
Version: 0.15.0
Summary: Light adapter classes around Open Babel, RDKit, and ChemAxon for the functionality needed in eQulibrator.
Home-page: https://gitlab.com/equilibrator/equilibrator-cheminfo
Download-URL: https://pypi.org/project/equilibrator-cheminfo/
Author: Moritz E. Beber, Elad Noor
Author-email: midnighter@posteo.net, eladnoor@protonmail.com
License: Apache-2.0
Project-URL: Source Code, https://gitlab.com/equilibrator/equilibrator-cheminfo
Project-URL: Documentation, https://equilibrator-cheminfo.readthedocs.io
Project-URL: Bug Tracker, https://gitlab.com/equilibrator/equilibrator-cheminfo/issues
Keywords: cheminformatics,OpenBabel,RDKit,ChemAxon,Marvin
Platform: UNKNOWN
Classifier: Development Status :: 2 - Pre-Alpha
Classifier: Intended Audience :: Science/Research
Classifier: License :: OSI Approved :: Apache Software License
Classifier: Natural Language :: English
Classifier: Operating System :: OS Independent
Classifier: Programming Language :: Python :: 3 :: Only
Classifier: Programming Language :: Python :: 3.8
Classifier: Programming Language :: Python :: 3.9
Classifier: Topic :: Scientific/Engineering :: Bio-Informatics
Classifier: Topic :: Scientific/Engineering :: Chemistry
Requires-Python: >=3.8
License-File: LICENSE
Requires-Dist: depinfo (~=1.7)
Requires-Dist: numpy (~=1.17)
Requires-Dist: pandas (~=1.2)
Requires-Dist: sqlalchemy (~=1.4)
Requires-Dist: tqdm (~=4.60)
Provides-Extra: chemaxon
Requires-Dist: jpype1 (~=1.3) ; extra == 'chemaxon'
Provides-Extra: development
Requires-Dist: black ; extra == 'development'
Requires-Dist: isort ; extra == 'development'
Requires-Dist: tox ; extra == 'development'
Provides-Extra: openbabel
Requires-Dist: openbabel-wheel (~=3.1) ; extra == 'openbabel'
Requires-Dist: periodictable (~=1.6) ; extra == 'openbabel'
Provides-Extra: rdkit
Requires-Dist: rdkit-pypi (~=2021.3) ; extra == 'rdkit'
